LICENSE
MANIFEST.in
README.md
requirements.txt
setup.py
src/__init__.py
src/main.py
src/include/__init__.py
src/include/im_innocent.py
src/include/rrsa.py
src/include/__pycache__/__init__.cpython-37.pyc
src/include/__pycache__/im_innocent.cpython-310.pyc
src/include/__pycache__/im_innocent.cpython-37.pyc
src/include/__pycache__/rrsa.cpython-37.pyc
src/include/keys/RSA_cmd_commands
src/include/keys/private.pem
src/include/keys/public.pem
wannaCry_Ransomware_EY.egg-info/PKG-INFO
wannaCry_Ransomware_EY.egg-info/SOURCES.txt
wannaCry_Ransomware_EY.egg-info/dependency_links.txt
wannaCry_Ransomware_EY.egg-info/requires.txt
wannaCry_Ransomware_EY.egg-info/top_level.txt